game_translator/__init__.py
game_translator/__main__.py
game_translator/_version.py
game_translator/game_translator.py
game_translator/audio/__init__.py
game_translator/audio/record.py
game_translator/aws_streaming_transcription/__init__.py
game_translator/aws_streaming_transcription/live_stream.py
game_translator/aws_streaming_transcription/prerecorded_stream.py
game_translator/aws_streaming_transcription/settings.py
game_translator/openai_translation/__init__.py
game_translator/openai_translation/chat.py
game_translator/xunfei_speed_transcription/__init__.py
game_translator/xunfei_speed_transcription/ost_fast.py
game_translator/xunfei_speed_transcription/seve_file.py
openai_game_translator-1.3.0.dist-info/LICENSE
openai_game_translator-1.3.0.dist-info/METADATA
openai_game_translator-1.3.0.dist-info/WHEEL
openai_game_translator-1.3.0.dist-info/entry_points.txt
openai_game_translator-1.3.0.dist-info/top_level.txt
openai_game_translator-1.3.0.dist-info/RECORD
