Metadata-Version: 2.1
Name: openai-game-translator
Version: 1.3.0
Summary: an openai based game audio translator
Author-email: Yuhan Xia <yx2729@columbia.edu>
License: Apache License
Project-URL: repository, https://github.com/Erisae/openai-game-translator
Classifier: Programming Language :: Python :: Implementation :: PyPy
Classifier: Programming Language :: Python :: 3.9
Classifier: Programming Language :: Python :: 3.10
Classifier: License :: OSI Approved :: Apache Software License
Classifier: Operating System :: OS Independent
Requires-Python: <3.11,>=3.9
License-File: LICENSE
Requires-Dist: aiofile (==3.8.5)
Requires-Dist: amazon-transcribe (==0.6.1)
Requires-Dist: numpy (==1.24.2)
Requires-Dist: openai (==0.27.2)
Requires-Dist: pyaudio (==0.2.13)
Requires-Dist: requests (==2.27.1)
Requires-Dist: urllib3 (==1.26.15)
Provides-Extra: develop
Requires-Dist: coverage (==7.2.2) ; extra == 'develop'
Requires-Dist: black (==23.3.0) ; extra == 'develop'
Requires-Dist: flake8 (==6.0.0) ; extra == 'develop'
Requires-Dist: build (==0.10.0) ; extra == 'develop'
Requires-Dist: twine (==4.0.2) ; extra == 'develop'
Requires-Dist: bump2version (==1.0.1) ; extra == 'develop'
Requires-Dist: check-manifest (==0.49) ; extra == 'develop'
